drf_serializer_dumps/__init__.py
drf_serializer_dumps/decorators.py
drf_serializer_dumps-1.0.6.dist-info/LICENSE
drf_serializer_dumps-1.0.6.dist-info/METADATA
drf_serializer_dumps-1.0.6.dist-info/WHEEL
drf_serializer_dumps-1.0.6.dist-info/entry_points.txt
drf_serializer_dumps-1.0.6.dist-info/top_level.txt
drf_serializer_dumps-1.0.6.dist-info/RECORD
