Metadata-Version: 2.1
Name: drf_serializer_dumps
Version: 1.0.6
Summary: Decorator for creating dict based on the drf serializer class for swagger
Home-page: https://github.com/Friskes/drf-serializer-dumps
Author: Friskes
Author-email: Friskes <friskesx@gmail.com>
License: MIT License
Project-URL: Homepage, https://github.com/Friskes/drf-serializer-dumps
Project-URL: Changelog, https://github.com/Friskes/drf-serializer-dumps/releases/
Project-URL: Issues, https://github.com/Friskes/drf-serializer-dumps/issues
Keywords: Django,DRF,Spectacular,Swagger
Classifier: Development Status :: 5 - Production/Stable
Classifier: Environment :: Web Environment
Classifier: Intended Audience :: Developers
Classifier: Operating System :: OS Independent
Classifier: License :: OSI Approved :: MIT License
Classifier: Programming Language :: Python :: 3.8
Classifier: Programming Language :: Python :: 3.9
Classifier: Programming Language :: Python :: 3.10
Classifier: Programming Language :: Python :: 3.11
Classifier: Programming Language :: Python :: 3.12
Classifier: Framework :: Django :: 3.2
Classifier: Framework :: Django :: 4.0
Classifier: Framework :: Django :: 4.1
Classifier: Framework :: Django :: 4.2
Classifier: Topic :: Internet :: WWW/HTTP
Classifier: Topic :: Documentation
Classifier: Topic :: Software Development :: Code Generators
Requires-Python: >=3.8
License-File: LICENSE
Requires-Dist: django>=4.2.11
Requires-Dist: djangorestframework>=3.14.0
Requires-Dist: drf-spectacular>=0.27.2
Provides-Extra: dev
Requires-Dist: psycopg2>=2.9.9; extra == "dev"
Requires-Dist: pre-commit>=3.5.0; extra == "dev"
Requires-Dist: ruff==0.8.0; extra == "dev"
Requires-Dist: pytest>=7.0.1; extra == "dev"
Requires-Dist: mypy>=1.10.0; extra == "dev"
Requires-Dist: pytest-cov>=5.0.0; extra == "dev"
Provides-Extra: ci
Requires-Dist: psycopg2>=2.9.9; extra == "ci"
Requires-Dist: ruff==0.8.0; extra == "ci"
Requires-Dist: pytest>=7.0.1; extra == "ci"
Requires-Dist: mypy>=1.10.0; extra == "ci"
Requires-Dist: pytest-cov>=5.0.0; extra == "ci"
